CalculateOT/__init__.py
CalculateOT/calculateOT.py
calculateDistributedOT-1.0.dist-info/LICENSE
calculateDistributedOT-1.0.dist-info/METADATA
calculateDistributedOT-1.0.dist-info/WHEEL
calculateDistributedOT-1.0.dist-info/top_level.txt
calculateDistributedOT-1.0.dist-info/RECORD
